torch_uncertainty/__init__.py
torch_uncertainty/callbacks/__init__.py
torch_uncertainty/callbacks/checkpoint.py
torch_uncertainty/callbacks/compound_checkpoint.py
torch_uncertainty/datamodules/__init__.py
torch_uncertainty/datamodules/abstract.py
torch_uncertainty/datamodules/classification/__init__.py
torch_uncertainty/datamodules/classification/cifar10.py
torch_uncertainty/datamodules/classification/cifar100.py
torch_uncertainty/datamodules/classification/imagenet.py
torch_uncertainty/datamodules/classification/mnist.py
torch_uncertainty/datamodules/classification/tiny_imagenet.py
torch_uncertainty/datamodules/classification/uci/__init__.py
torch_uncertainty/datamodules/classification/uci/bank_marketing.py
torch_uncertainty/datamodules/classification/uci/dota2_games.py
torch_uncertainty/datamodules/classification/uci/htru2.py
torch_uncertainty/datamodules/classification/uci/online_shoppers.py
torch_uncertainty/datamodules/classification/uci/spam_base.py
torch_uncertainty/datamodules/classification/uci/uci_classification.py
torch_uncertainty/datamodules/classification/ucr_uea.py
torch_uncertainty/datamodules/depth/__init__.py
torch_uncertainty/datamodules/depth/base.py
torch_uncertainty/datamodules/depth/kitti.py
torch_uncertainty/datamodules/depth/muad.py
torch_uncertainty/datamodules/depth/nyu.py
torch_uncertainty/datamodules/segmentation/__init__.py
torch_uncertainty/datamodules/segmentation/camvid.py
torch_uncertainty/datamodules/segmentation/cityscapes.py
torch_uncertainty/datamodules/segmentation/muad.py
torch_uncertainty/datamodules/uci_regression.py
torch_uncertainty/datasets/__init__.py
torch_uncertainty/datasets/aggregated_dataset.py
torch_uncertainty/datasets/classification/__init__.py
torch_uncertainty/datasets/classification/cifar/__init__.py
torch_uncertainty/datasets/classification/cifar/cifar_c.py
torch_uncertainty/datasets/classification/cifar/cifar_h.py
torch_uncertainty/datasets/classification/cifar/cifar_n.py
torch_uncertainty-0.8.0.dist-info/WHEEL
torch_uncertainty-0.8.0.dist-info/METADATA
torch_uncertainty-0.8.0.dist-info/RECORD
