Metadata-Version: 2.3
Name: torch-uncertainty
Version: 0.8.0
Summary: Uncertainty quantification library in PyTorch
Keywords: bayesian-network,ensembles,neural-networks,predictive-uncertainty,reliable-ai,trustworthy-machine-learning,uncertainty,uncertainty-quantification
Author: ENSTA U2IS AI, Adrien Lafage, Olivier Laurent
Author-email: ENSTA U2IS AI <olivier.laurent@ensta.fr>, Adrien Lafage <adrienlafage@outlook.com>, Olivier Laurent <olivier.ar.laurent@gmail.com>
Classifier: License :: OSI Approved :: Apache Software License
Classifier: Programming Language :: Python :: 3 :: Only
Classifier: Programming Language :: Python :: 3.10
Classifier: Programming Language :: Python :: 3.11
Classifier: Programming Language :: Python :: 3.12
Classifier: Programming Language :: Python :: 3.13
Requires-Dist: timm
Requires-Dist: lightning[pytorch-extra]>=2.0,<2.7
Requires-Dist: torch>=2.1,<2.9
Requires-Dist: torchvision>=0.16
Requires-Dist: einops
Requires-Dist: seaborn
Requires-Dist: torch-uncertainty[experiments,image,distribution,timeseries,others] ; extra == 'all'
Requires-Dist: torch>=2.1.0,<2.9 ; extra == 'cpu'
Requires-Dist: torchvision>=0.16.0 ; extra == 'cpu'
Requires-Dist: scipy ; extra == 'distribution'
Requires-Dist: tensorboard ; extra == 'experiments'
Requires-Dist: huggingface-hub>=0.31 ; extra == 'experiments'
Requires-Dist: safetensors ; extra == 'experiments'
Requires-Dist: torch>=2.1.0,<2.9 ; extra == 'gpu'
Requires-Dist: torchvision>=0.16.0 ; extra == 'gpu'
Requires-Dist: kornia ; extra == 'image'
Requires-Dist: h5py ; extra == 'image'
Requires-Dist: opencv-python ; extra == 'image'
Requires-Dist: torch-uncertainty-assets ; extra == 'image'
Requires-Dist: scikit-learn ; extra == 'others'
Requires-Dist: curvlinops-for-pytorch<3 ; extra == 'others'
Requires-Dist: laplace-torch ; extra == 'others'
Requires-Dist: glest==0.0.1a1 ; extra == 'others'
Requires-Dist: tslearn ; extra == 'timeseries'
Requires-Python: >=3.10, <=3.14
Project-URL: documentation, https://torch-uncertainty.github.io/quickstart.html
Project-URL: homepage, https://torch-uncertainty.github.io/
Project-URL: repository, https://github.com/ENSTA-U2IS-AI/torch-uncertainty.git
Provides-Extra: all
Provides-Extra: cpu
Provides-Extra: distribution
Provides-Extra: experiments
Provides-Extra: gpu
Provides-Extra: image
Provides-Extra: others
Provides-Extra: timeseries
